py_me/__init__.py
py_me/music_me.py
py_me/os_me.py
py_me/project_me.py
py_me/tk_me.py
py_me-3.5.4.dist-info/licenses/LICENSE.txt
py_me-3.5.4.dist-info/METADATA
py_me-3.5.4.dist-info/WHEEL
py_me-3.5.4.dist-info/top_level.txt
py_me-3.5.4.dist-info/RECORD
