Metadata-Version: 2.4
Name: py_me
Version: 3.5.4
Summary: Python library with modules for sounds, graphical interface, semi-automatic creation of Python projects, and advanced file manipulation.
Author: isaias da silva nobrega
Author-email: Isaias da Silva Nobrega <isaiasdasilvanobrega@gmail.com>
Maintainer-email: Isaias da Silva Nobrega <isaiasdasilvanobrega@gmail.com>
Project-URL: Homepage, https://github.com/rip-mine2023/py_me
Project-URL: Source, https://github.com/rip-mine2023/py_me
Project-URL: Issues, https://github.com/rip-mine2023/py_me/issues
Keywords: pygame,pydub,audio,music,tkinter,sound,interface,Python,biblioteca, projetos, project, os
Classifier: Programming Language :: Python :: 3
Classifier: Topic :: Multimedia :: Sound/Audio
Classifier: Topic :: Software Development :: Libraries
Classifier: Intended Audience :: Developers
Classifier: Operating System :: OS Independent
Requires-Python: >=3.7
License-File: LICENSE.txt
Requires-Dist: pygame
Requires-Dist: pydub
Requires-Dist: rich
Dynamic: author
Dynamic: license-file
